vlm/__init__.py
vlm/__main__.py
vlm/py.typed
vlm/vlm.py
vlm/config/__init__.py
vlm/config/config.yaml
vlm/config/config_schema.py
vlm/config/finetune-llama.yaml
vlm/config/finetune-llava.yaml
vlm/config/finetune-qwen.yaml
vlm/config/pretrain-llama.yaml
vlm/config/pretrain-llava.yaml
vlm/config/pretrain-qwen.yaml
vlm/config/dataset/llava-finetune.yaml
vlm/config/dataset/llava-pretrain.yaml
vlm/config/deepspeed/zero2.json
vlm/config/deepspeed/zero3.json
vlm/config/deepspeed/zero3_offload.json
vlm/config/hydra/job_logging/rich.yaml
vlm/config/inference/default.yaml
vlm/config/model/llama3.2-3b.yaml
vlm/config/model/llava-7b.yaml
vlm/config/model/qwen3-1.7b.yaml
vlm/config/model/qwen3-8b.yaml
vlm/config/trainer/finetune.yaml
vlm/config/trainer/pretrain.yaml
vlm/config/trainer/learning_rate/default.yaml
vlm/config/trainer/learning_rate/llava-finetune.yaml
vlm/config/trainer/learning_rate/llava-next-finetune.yaml
vlm/config/trainer/learning_rate/llava-pretrain.yaml
vlm/config/trainer/unfreeze/finetune.yaml
vlm/config/trainer/unfreeze/frozen.yaml
vlm/config/trainer/unfreeze/pretrain.yaml
vlm/config/trainer/unfreeze/unfrozen.yaml
vlm/config/trainer/weight_decay/default.yaml
vlm/data/__init__.py
vlm/data/data_arguments.py
vlm/data/dataset.py
vlm/data/sampler.py
vlm/inference/__init__.py
vlm/inference/eval.py
vlm/inference/generator.py
vlm/inference/lmms_eval.py
vlm/models/__init__.py
vlm/models/configuration_vlm.py
vlm/models/connectors.py
vlm/models/modeling_vlm.py
vlm/models/processing_vlm.py
vlm/train/__init__.py
vlm/train/optimizer.py
vlm/train/set_trainable.py
vlm/train/train.py
vlm/train/training_arguments.py
vlm/train/vlm_trainer.py
vlm/utils/__init__.py
vlm/utils/conversation.py
vlm/utils/logging_utils.py
vlm/utils/push_to_hub.py
small_vlm-0.9.2.dist-info/METADATA
small_vlm-0.9.2.dist-info/WHEEL
small_vlm-0.9.2.dist-info/entry_points.txt
small_vlm-0.9.2.dist-info/licenses/LICENSE
small_vlm-0.9.2.dist-info/RECORD
