Metadata-Version: 2.4
Name: small-vlm
Version: 0.9.2
Summary: small vlm for training and experiments
Project-URL: Repository, https://github.com/leo1oel/small-vlm
Author-email: Yiming Liu <liuym23@mails.tsinghua.edu.cn>
License-Expression: MIT
License-File: LICENSE
Classifier: Development Status :: 4 - Beta
Classifier: Intended Audience :: Developers
Classifier: Operating System :: OS Independent
Classifier: Programming Language :: Python
Classifier: Programming Language :: Python :: 3
Classifier: Programming Language :: Python :: 3.11
Classifier: Programming Language :: Python :: 3.12
Classifier: Programming Language :: Python :: 3.13
Classifier: Typing :: Typed
Requires-Python: <4.0,>=3.11
Requires-Dist: accelerate==1.6.0
Requires-Dist: blobfile==3.0.0
Requires-Dist: deepspeed==0.16.7
Requires-Dist: hydra-core==1.3.2
Requires-Dist: pillow==11.2.1
Requires-Dist: protobuf==6.30.2
Requires-Dist: rich==14.0.0
Requires-Dist: sentencepiece==0.2.0
Requires-Dist: tiktoken==0.9.0
Requires-Dist: torch==2.6.0
Requires-Dist: torchvision==0.21.0
Requires-Dist: transformers==4.51.3
Requires-Dist: wandb==0.19.10
